{"years": {"2014": {"observations": {"INNOVATION": {"value": 42.0, "rank": 31, "rank_change": 2}, "IMPLEMENTATION": {"value": 37.0, "rank": 37, "rank_change": -8}, "ODB.2013.C.INIT": {"value": 5.0, "rank": 31, "rank_change": -10}, "ODB.2013.I.INC": {"value": 0.0, "rank": 21, "rank_change": -17}, "ODB.2013.C.RTI": {"value": 3.0, "rank": 59, "rank_change": -7}, "FH": {"value": 80.0, "rank": 36, "rank_change": 0}, "UN.OSI": {"value": 0.55118, "rank": 45, "rank_change": -4}, "ODB.2013.C.CITY": {"value": 4.0, "rank": 24, "rank_change": -6}, "REGULATORY_AND_CIVIL": {"value": 60.0, "rank": 38, "rank_change": -3}, "POLITICAL": {"value": 22.0, "rank": 36, "rank_change": 6}, "ODB.2013.D7": {"value": 15.0, "rank": 16, "rank_change": 31}, "ODB.2013.D8": {"value": 15.0, "rank": 14, "rank_change": -1}, "GOVERNMENT_ACTION": {"value": 42.0, "rank": 50, "rank_change": -5}, "ODB.2013.D6": {"value": 15.0, "rank": 24, "rank_change": 4}, "ODB.2013.C.CSOC": {"value": 4.0, "rank": 40, "rank_change": 2}, "ODB.2013.I.ENTR": {"value": 2.0, "rank": 26, "rank_change": 12}, "READINESS": {"value": 48.0, "rank": 42, "rank_change": -5}, "SOCIAL_POLICY": {"value": 38.0, "rank": 49, "rank_change": -29}, "SOCIAL": {"value": 17.0, "rank": 19, "rank_change": -10}, "ODB.2013.I.ECON": {"value": 1.0, "rank": 25, "rank_change": 3}, "BUSINESS_AND_ENTREPRENEURSHIP": {"value": 44.0, "rank": 46, "rank_change": -9}, "ACCOUNTABILITY": {"value": 31.0, "rank": 33, "rank_change": 1}, "ODB.2013.D9": {"value": 95.0, "rank": 2, "rank_change": 41}, "ODB.2013.D12": {"value": 80.0, "rank": 11, "rank_change": 8}, "ODB.2013.C.SUPIN": {"value": 3.0, "rank": 22, "rank_change": -9}, "IMPACT": {"value": 23.0, "rank": 30, "rank_change": 2}, "ECONOMIC": {"value": 20.0, "rank": 28, "rank_change": 15}, "ODB.2013.I.GOV": {"value": 0.0, "rank": 41, "rank_change": -4}, "ODB.2013.D4": {"value": 80.0, "rank": 14, "rank_change": -2}, "ODB.2013.D11": {"value": 15.0, "rank": 51, "rank_change": -22}, "WB.NETUSERS": {"value": 59.9, "rank": 35, "rank_change": -2}, "ODB.2013.D13": {"value": 10.0, "rank": 54, "rank_change": 2}, "ODB.2013.D10": {"value": 10.0, "rank": 71, "rank_change": -50}, "WEF.GCI.9.02": {"value": 4.106196425, "rank": 72, "rank_change": -5}, "ODB.2013.I.ACCOUNT": {"value": 3.0, "rank": 18, "rank_change": 7}, "ODB.2013.D14": {"value": 10.0, "rank": 50, "rank_change": -32}, "ODB.2013.D1": {"value": 80.0, "rank": 11, "rank_change": 15}, "ODB.2013.D15": {"value": 95.0, "rank": 2, "rank_change": -1}, "ODB.2013.D16": {"value": 15.0, "rank": 15, "rank_change": null}, "WEF.GITR.8.01": {"value": 2.524871809, "rank": 84, "rank_change": -9}, "ODB.2013.I.ENV": {"value": 2.0, "rank": 12, "rank_change": 4}, "ODB": {"value": 35.71, "rank": 36, "rank_change": -5}, "ODB.2013.C.TRAIN": {"value": 3.0, "rank": 43, "rank_change": -16}, "ODB.2013.C.DPL": {"value": 8.0, "rank": 10, "rank_change": -6}, "ODB.2013.D2": {"value": 5.0, "rank": 37, "rank_change": -8}, "ODB.2013.D5": {"value": 15.0, "rank": 39, "rank_change": -5}}, "stats": {"INNOVATION": {"median": 42.0, "mean": 42.0}, "IMPLEMENTATION": {"median": 37.0, "mean": 37.0}, "ODB.2013.C.INIT": {"median": 5.0, "mean": 5.0}, "ODB.2013.I.INC": {"median": 0.0, "mean": 0.0}, "ODB.2013.C.RTI": {"median": 3.0, "mean": 3.0}, "FH": {"median": 80.0, "mean": 80.0}, "UN.OSI": {"median": 0.55118, "mean": 0.55118}, "ODB.2013.C.CITY": {"median": 4.0, "mean": 4.0}, "REGULATORY_AND_CIVIL": {"median": 60.0, "mean": 60.0}, "POLITICAL": {"median": 22.0, "mean": 22.0}, "ODB.2013.D7": {"median": 15.0, "mean": 15.0}, "ODB.2013.D8": {"median": 15.0, "mean": 15.0}, "GOVERNMENT_ACTION": {"median": 42.0, "mean": 42.0}, "ODB.2013.D6": {"median": 15.0, "mean": 15.0}, "ODB.2013.C.CSOC": {"median": 4.0, "mean": 4.0}, "ODB.2013.I.ENTR": {"median": 2.0, "mean": 2.0}, "READINESS": {"median": 48.0, "mean": 48.0}, "SOCIAL_POLICY": {"median": 38.0, "mean": 38.0}, "SOCIAL": {"median": 17.0, "mean": 17.0}, "ODB.2013.I.ECON": {"median": 1.0, "mean": 1.0}, "BUSINESS_AND_ENTREPRENEURSHIP": {"median": 44.0, "mean": 44.0}, "ACCOUNTABILITY": {"median": 31.0, "mean": 31.0}, "ODB.2013.D9": {"median": 95.0, "mean": 95.0}, "ODB.2013.D12": {"median": 80.0, "mean": 80.0}, "ODB.2013.C.SUPIN": {"median": 3.0, "mean": 3.0}, "IMPACT": {"median": 23.0, "mean": 23.0}, "ECONOMIC": {"median": 20.0, "mean": 20.0}, "ODB.2013.I.GOV": {"median": 0.0, "mean": 0.0}, "ODB.2013.D4": {"median": 80.0, "mean": 80.0}, "ODB.2013.D11": {"median": 15.0, "mean": 15.0}, "WB.NETUSERS": {"median": 59.9, "mean": 59.9}, "ODB.2013.D13": {"median": 10.0, "mean": 10.0}, "ODB.2013.D10": {"median": 10.0, "mean": 10.0}, "WEF.GCI.9.02": {"median": 4.106196425, "mean": 4.106196425}, "ODB.2013.I.ACCOUNT": {"median": 3.0, "mean": 3.0}, "ODB.2013.D14": {"median": 10.0, "mean": 10.0}, "ODB.2013.D1": {"median": 80.0, "mean": 80.0}, "ODB.2013.D15": {"median": 95.0, "mean": 95.0}, "ODB.2013.D16": {"median": 15.0, "mean": 15.0}, "WEF.GITR.8.01": {"median": 2.524871809, "mean": 2.524871809}, "ODB.2013.I.ENV": {"median": 2.0, "mean": 2.0}, "ODB": {"median": 35.71, "mean": 35.71}, "ODB.2013.C.TRAIN": {"median": 3.0, "mean": 3.0}, "ODB.2013.C.DPL": {"median": 8.0, "mean": 8.0}, "ODB.2013.D2": {"median": 5.0, "mean": 5.0}, "ODB.2013.D5": {"median": 15.0, "mean": 15.0}}, "datasets": {"ODB.2013.D11": {"DBULK": 0.0, "ISOPEN": 0.0, "EFREE": 0.0, "GUPDATED": 0.0, "IDISCOVERABLE": 0.0, "BAVAILABLE": 10.0, "FLICENSE": 0.0, "HSUSTAINABLE": 0.0, "CMACHINEREADABLE": 0.0, "VALUE": 15.0, "AEXISTS": 5.0, "JLINKED": 0.0}, "ODB.2013.D1": {"DBULK": 15.0, "ISOPEN": 0.0, "EFREE": 15.0, "GUPDATED": 10.0, "IDISCOVERABLE": 5.0, "BAVAILABLE": 10.0, "FLICENSE": 0.0, "HSUSTAINABLE": 5.0, "CMACHINEREADABLE": 15.0, "VALUE": 80.0, "AEXISTS": 5.0, "JLINKED": 0.0}, "ODB.2013.D15": {"DBULK": 15.0, "ISOPEN": 1.0, "EFREE": 15.0, "GUPDATED": 10.0, "IDISCOVERABLE": 5.0, "BAVAILABLE": 10.0, "FLICENSE": 15.0, "HSUSTAINABLE": 5.0, "CMACHINEREADABLE": 15.0, "VALUE": 95.0, "AEXISTS": 5.0, "JLINKED": 0.0}, "ODB.2013.D14": {"DBULK": 0.0, "ISOPEN": 0.0, "EFREE": 0.0, "GUPDATED": -5.0, "IDISCOVERABLE": 0.0, "BAVAILABLE": 10.0, "FLICENSE": 0.0, "HSUSTAINABLE": 0.0, "CMACHINEREADABLE": 0.0, "VALUE": 10.0, "AEXISTS": 5.0, "JLINKED": 0.0}, "ODB.2013.D4": {"DBULK": 15.0, "ISOPEN": 0.0, "EFREE": 15.0, "GUPDATED": 10.0, "IDISCOVERABLE": 5.0, "BAVAILABLE": 10.0, "FLICENSE": 0.0, "HSUSTAINABLE": 5.0, "CMACHINEREADABLE": 15.0, "VALUE": 80.0, "AEXISTS": 5.0, "JLINKED": 0.0}, "ODB.2013.D5": {"DBULK": 0.0, "ISOPEN": 0.0, "EFREE": 0.0, "GUPDATED": 0.0, "IDISCOVERABLE": 0.0, "BAVAILABLE": 10.0, "FLICENSE": 0.0, "HSUSTAINABLE": 0.0, "CMACHINEREADABLE": 0.0, "VALUE": 15.0, "AEXISTS": 5.0, "JLINKED": 0.0}, "ODB.2013.D13": {"DBULK": 0.0, "ISOPEN": 0.0, "EFREE": 0.0, "GUPDATED": -5.0, "IDISCOVERABLE": 0.0, "BAVAILABLE": 10.0, "FLICENSE": 0.0, "HSUSTAINABLE": 0.0, "CMACHINEREADABLE": 0.0, "VALUE": 10.0, "AEXISTS": 5.0, "JLINKED": 0.0}, "ODB.2013.D10": {"DBULK": 0.0, "ISOPEN": 0.0, "EFREE": 0.0, "GUPDATED": -5.0, "IDISCOVERABLE": 0.0, "BAVAILABLE": 10.0, "FLICENSE": 0.0, "HSUSTAINABLE": 0.0, "CMACHINEREADABLE": 0.0, "VALUE": 10.0, "AEXISTS": 5.0, "JLINKED": 0.0}, "ODB.2013.D7": {"DBULK": 0.0, "ISOPEN": 0.0, "EFREE": 0.0, "GUPDATED": 0.0, "IDISCOVERABLE": 0.0, "BAVAILABLE": 10.0, "FLICENSE": 0.0, "HSUSTAINABLE": 0.0, "CMACHINEREADABLE": 0.0, "VALUE": 15.0, "AEXISTS": 5.0, "JLINKED": 0.0}, "ODB.2013.D9": {"DBULK": 15.0, "ISOPEN": 1.0, "EFREE": 15.0, "GUPDATED": 10.0, "IDISCOVERABLE": 5.0, "BAVAILABLE": 10.0, "FLICENSE": 15.0, "HSUSTAINABLE": 5.0, "CMACHINEREADABLE": 15.0, "VALUE": 95.0, "AEXISTS": 5.0, "JLINKED": 0.0}, "ODB.2013.D2": {"DBULK": 0.0, "ISOPEN": 0.0, "EFREE": 0.0, "GUPDATED": 0.0, "IDISCOVERABLE": 0.0, "BAVAILABLE": 0.0, "FLICENSE": 0.0, "HSUSTAINABLE": 0.0, "CMACHINEREADABLE": 0.0, "VALUE": 5.0, "AEXISTS": 5.0, "JLINKED": 0.0}, "ODB.2013.D6": {"DBULK": 0.0, "ISOPEN": 0.0, "EFREE": 0.0, "GUPDATED": 0.0, "IDISCOVERABLE": 0.0, "BAVAILABLE": 10.0, "FLICENSE": 0.0, "HSUSTAINABLE": 0.0, "CMACHINEREADABLE": 0.0, "VALUE": 15.0, "AEXISTS": 5.0, "JLINKED": 0.0}, "ODB.2013.D8": {"DBULK": 0.0, "ISOPEN": 0.0, "EFREE": 0.0, "GUPDATED": 0.0, "IDISCOVERABLE": 0.0, "BAVAILABLE": 10.0, "FLICENSE": 0.0, "HSUSTAINABLE": 0.0, "CMACHINEREADABLE": 0.0, "VALUE": 15.0, "AEXISTS": 5.0, "JLINKED": 0.0}, "ODB.2013.D12": {"DBULK": 15.0, "ISOPEN": 1.0, "EFREE": 15.0, "GUPDATED": -5.0, "IDISCOVERABLE": 5.0, "BAVAILABLE": 10.0, "FLICENSE": 15.0, "HSUSTAINABLE": 5.0, "CMACHINEREADABLE": 15.0, "VALUE": 80.0, "AEXISTS": 5.0, "JLINKED": 0.0}, "ODB.2013.D16": {"DBULK": 0.0, "ISOPEN": 0.0, "EFREE": 0.0, "GUPDATED": 0.0, "IDISCOVERABLE": 0.0, "BAVAILABLE": 10.0, "FLICENSE": 0.0, "HSUSTAINABLE": 0.0, "CMACHINEREADABLE": 0.0, "VALUE": 15.0, "AEXISTS": 5.0, "JLINKED": 0.0}}}, "2015": {"observations": {"ODB.2015.C.POLI": {"value": 3.0, "rank": 40, "rank_change": null}, "INNOVATION": {"value": 23.0, "rank": 56, "rank_change": -25}, "IMPLEMENTATION": {"value": 21.0, "rank": 53, "rank_change": -16}, "ODB.2013.C.INIT": {"value": 5.0, "rank": 35, "rank_change": -4}, "ODB.2013.I.INC": {"value": 0.0, "rank": 26, "rank_change": -5}, "ODB.2013.C.RTI": {"value": 4.0, "rank": 46, "rank_change": 13}, "SOCIAL_POLICY": {"value": 20.0, "rank": 67, "rank_change": -18}, "FH": {"value": 80.0, "rank": 38, "rank_change": -2}, "UN.OSI": {"value": 0.55118, "rank": 47, "rank_change": -2}, "ODB.2013.C.CITY": {"value": 5.0, "rank": 18, "rank_change": 6}, "REGULATORY_AND_CIVIL": {"value": 62.0, "rank": 42, "rank_change": -4}, "POLITICAL": {"value": 10.0, "rank": 43, "rank_change": -7}, "GOVERNMENT_POLICIES": {"value": 18.0, "rank": 80, "rank_change": null}, "ODB.2013.D7": {"value": 0.0, "rank": 91, "rank_change": -75}, "ODB.2013.D8": {"value": 15.0, "rank": 17, "rank_change": -3}, "GOVERNMENT_ACTION": {"value": 56.0, "rank": 32, "rank_change": 18}, "ODB.2013.D6": {"value": 5.0, "rank": 5, "rank_change": 19}, "ODB.2013.C.CSOC": {"value": 4.0, "rank": 49, "rank_change": -9}, "ODB.2013.I.ENTR": {"value": 1.0, "rank": 40, "rank_change": -14}, "READINESS": {"value": 42.0, "rank": 49, "rank_change": -7}, "ODB.2015.C.MANAG": {"value": 1.0, "rank": 48, "rank_change": null}, "SOCIAL": {"value": 10.0, "rank": 33, "rank_change": -14}, "ODB.2013.I.ECON": {"value": 1.0, "rank": 30, "rank_change": -5}, "BUSINESS_AND_ENTREPRENEURSHIP": {"value": 39.0, "rank": 53, "rank_change": -7}, "ACCOUNTABILITY": {"value": 33.0, "rank": 35, "rank_change": -2}, "ODB.2013.D9": {"value": 15.0, "rank": 27, "rank_change": -25}, "ODB.2013.D12": {"value": 5.0, "rank": 81, "rank_change": -70}, "ODB.2013.C.SUPIN": {"value": 3.0, "rank": 33, "rank_change": -11}, "IMPACT": {"value": 11.0, "rank": 46, "rank_change": -16}, "ECONOMIC": {"value": 13.0, "rank": 36, "rank_change": -8}, "ODB.2013.I.GOV": {"value": 0.0, "rank": 49, "rank_change": -8}, "ODB.2013.D4": {"value": 75.0, "rank": 38, "rank_change": -24}, "ODB.2013.D11": {"value": 15.0, "rank": 54, "rank_change": -3}, "WB.NETUSERS": {"value": 64.7, "rank": 35, "rank_change": 0}, "ODB.2013.D13": {"value": 15.0, "rank": 45, "rank_change": 9}, "ODB.2013.D10": {"value": 15.0, "rank": 63, "rank_change": 8}, "WEF.GCI.9.02": {"value": 4.028446775, "rank": 78, "rank_change": -6}, "ODB.2013.I.ACCOUNT": {"value": 1.0, "rank": 35, "rank_change": -17}, "ODB.2013.D14": {"value": 0.0, "rank": 80, "rank_change": -30}, "ODB.2013.D1": {"value": 55.0, "rank": 33, "rank_change": -22}, "ODB.2013.D15": {"value": 80.0, "rank": 12, "rank_change": -10}, "ODB.2013.D16": {"value": 15.0, "rank": 22, "rank_change": -7}, "WEF.GITR.8.01": {"value": 2.478687732, "rank": 89, "rank_change": -5}, "ODB.2013.I.ENV": {"value": 1.0, "rank": 20, "rank_change": -8}, "ODB": {"value": 23.78, "rank": 52, "rank_change": -16}, "ODB.2013.C.TRAIN": {"value": 3.0, "rank": 51, "rank_change": -8}, "ODB.2013.C.DPL": {"value": 7.0, "rank": 28, "rank_change": -18}, "ODB.2013.D2": {"value": 5.0, "rank": 43, "rank_change": -6}, "ODB.2013.D5": {"value": 65.0, "rank": 31, "rank_change": 8}}, "stats": {"ODB.2015.C.POLI": {"median": 3.0, "mean": 3.0}, "INNOVATION": {"median": 23.0, "mean": 23.0}, "IMPLEMENTATION": {"median": 21.0, "mean": 21.0}, "ODB.2013.C.INIT": {"median": 5.0, "mean": 5.0}, "ODB.2013.I.INC": {"median": 0.0, "mean": 0.0}, "ODB.2013.C.RTI": {"median": 4.0, "mean": 4.0}, "SOCIAL_POLICY": {"median": 20.0, "mean": 20.0}, "FH": {"median": 80.0, "mean": 80.0}, "UN.OSI": {"median": 0.55118, "mean": 0.55118}, "ODB.2013.C.CITY": {"median": 5.0, "mean": 5.0}, "REGULATORY_AND_CIVIL": {"median": 62.0, "mean": 62.0}, "POLITICAL": {"median": 10.0, "mean": 10.0}, "GOVERNMENT_POLICIES": {"median": 18.0, "mean": 18.0}, "ODB.2013.D7": {"median": 0.0, "mean": 0.0}, "ODB.2013.D8": {"median": 15.0, "mean": 15.0}, "GOVERNMENT_ACTION": {"median": 56.0, "mean": 56.0}, "ODB.2013.D6": {"median": 5.0, "mean": 5.0}, "ODB.2013.C.CSOC": {"median": 4.0, "mean": 4.0}, "ODB.2013.I.ENTR": {"median": 1.0, "mean": 1.0}, "READINESS": {"median": 42.0, "mean": 42.0}, "ODB.2015.C.MANAG": {"median": 1.0, "mean": 1.0}, "SOCIAL": {"median": 10.0, "mean": 10.0}, "ODB.2013.I.ECON": {"median": 1.0, "mean": 1.0}, "BUSINESS_AND_ENTREPRENEURSHIP": {"median": 39.0, "mean": 39.0}, "ACCOUNTABILITY": {"median": 33.0, "mean": 33.0}, "ODB.2013.D9": {"median": 15.0, "mean": 15.0}, "ODB.2013.D12": {"median": 5.0, "mean": 5.0}, "ODB.2013.C.SUPIN": {"median": 3.0, "mean": 3.0}, "IMPACT": {"median": 11.0, "mean": 11.0}, "ECONOMIC": {"median": 13.0, "mean": 13.0}, "ODB.2013.I.GOV": {"median": 0.0, "mean": 0.0}, "ODB.2013.D4": {"median": 75.0, "mean": 75.0}, "ODB.2013.D11": {"median": 15.0, "mean": 15.0}, "WB.NETUSERS": {"median": 64.7, "mean": 64.7}, "ODB.2013.D13": {"median": 15.0, "mean": 15.0}, "ODB.2013.D10": {"median": 15.0, "mean": 15.0}, "WEF.GCI.9.02": {"median": 4.028446775, "mean": 4.028446775}, "ODB.2013.I.ACCOUNT": {"median": 1.0, "mean": 1.0}, "ODB.2013.D14": {"median": 0.0, "mean": 0.0}, "ODB.2013.D1": {"median": 55.0, "mean": 55.0}, "ODB.2013.D15": {"median": 80.0, "mean": 80.0}, "ODB.2013.D16": {"median": 15.0, "mean": 15.0}, "WEF.GITR.8.01": {"median": 2.478687732, "mean": 2.478687732}, "ODB.2013.I.ENV": {"median": 1.0, "mean": 1.0}, "ODB": {"median": 23.78, "mean": 23.78}, "ODB.2013.C.TRAIN": {"median": 3.0, "mean": 3.0}, "ODB.2013.C.DPL": {"median": 7.0, "mean": 7.0}, "ODB.2013.D2": {"median": 5.0, "mean": 5.0}, "ODB.2013.D5": {"median": 65.0, "mean": 65.0}}, "datasets": {"ODB.2013.D11": {"DBULK": 0.0, "ISOPEN": 0.0, "EFREE": 0.0, "GUPDATED": 0.0, "IDISCOVERABLE": 0.0, "BAVAILABLE": 10.0, "FLICENSE": 0.0, "HSUSTAINABLE": 0.0, "CMACHINEREADABLE": 0.0, "VALUE": 15.0, "AEXISTS": 5.0, "JLINKED": 0.0}, "ODB.2013.D1": {"DBULK": 15.0, "ISOPEN": 0.0, "EFREE": 15.0, "GUPDATED": -5.0, "IDISCOVERABLE": 0.0, "BAVAILABLE": 10.0, "FLICENSE": 0.0, "HSUSTAINABLE": 0.0, "CMACHINEREADABLE": 15.0, "VALUE": 55.0, "AEXISTS": 5.0, "JLINKED": 0.0}, "ODB.2013.D15": {"DBULK": 15.0, "ISOPEN": 0.0, "EFREE": 15.0, "GUPDATED": 10.0, "IDISCOVERABLE": 5.0, "BAVAILABLE": 10.0, "FLICENSE": 0.0, "HSUSTAINABLE": 5.0, "CMACHINEREADABLE": 15.0, "VALUE": 80.0, "AEXISTS": 5.0, "JLINKED": 0.0}, "ODB.2013.D14": {"DBULK": 0.0, "ISOPEN": 0.0, "EFREE": 0.0, "GUPDATED": 0.0, "IDISCOVERABLE": 0.0, "BAVAILABLE": 0.0, "FLICENSE": 0.0, "HSUSTAINABLE": 0.0, "CMACHINEREADABLE": 0.0, "VALUE": 0.0, "AEXISTS": 0.0, "JLINKED": 0.0}, "ODB.2013.D4": {"DBULK": 15.0, "ISOPEN": 0.0, "EFREE": 15.0, "GUPDATED": 10.0, "IDISCOVERABLE": 5.0, "BAVAILABLE": 10.0, "FLICENSE": 0.0, "HSUSTAINABLE": 0.0, "CMACHINEREADABLE": 15.0, "VALUE": 75.0, "AEXISTS": 5.0, "JLINKED": 0.0}, "ODB.2013.D5": {"DBULK": 0.0, "ISOPEN": 0.0, "EFREE": 15.0, "GUPDATED": 10.0, "IDISCOVERABLE": 5.0, "BAVAILABLE": 10.0, "FLICENSE": 0.0, "HSUSTAINABLE": 5.0, "CMACHINEREADABLE": 15.0, "VALUE": 65.0, "AEXISTS": 5.0, "JLINKED": 0.0}, "ODB.2013.D13": {"DBULK": 0.0, "ISOPEN": 0.0, "EFREE": 0.0, "GUPDATED": 0.0, "IDISCOVERABLE": 0.0, "BAVAILABLE": 10.0, "FLICENSE": 0.0, "HSUSTAINABLE": 0.0, "CMACHINEREADABLE": 0.0, "VALUE": 15.0, "AEXISTS": 5.0, "JLINKED": 0.0}, "ODB.2013.D10": {"DBULK": 0.0, "ISOPEN": 0.0, "EFREE": 0.0, "GUPDATED": 0.0, "IDISCOVERABLE": 0.0, "BAVAILABLE": 10.0, "FLICENSE": 0.0, "HSUSTAINABLE": 0.0, "CMACHINEREADABLE": 0.0, "VALUE": 15.0, "AEXISTS": 5.0, "JLINKED": 0.0}, "ODB.2013.D7": {"DBULK": 0.0, "ISOPEN": 0.0, "EFREE": 0.0, "GUPDATED": 0.0, "IDISCOVERABLE": 0.0, "BAVAILABLE": 0.0, "FLICENSE": 0.0, "HSUSTAINABLE": 0.0, "CMACHINEREADABLE": 0.0, "VALUE": 0.0, "AEXISTS": 0.0, "JLINKED": 0.0}, "ODB.2013.D9": {"DBULK": 0.0, "ISOPEN": 0.0, "EFREE": 0.0, "GUPDATED": 0.0, "IDISCOVERABLE": 0.0, "BAVAILABLE": 10.0, "FLICENSE": 0.0, "HSUSTAINABLE": 0.0, "CMACHINEREADABLE": 0.0, "VALUE": 15.0, "AEXISTS": 5.0, "JLINKED": 0.0}, "ODB.2013.D2": {"DBULK": 0.0, "ISOPEN": 0.0, "EFREE": 0.0, "GUPDATED": 0.0, "IDISCOVERABLE": 0.0, "BAVAILABLE": 0.0, "FLICENSE": 0.0, "HSUSTAINABLE": 0.0, "CMACHINEREADABLE": 0.0, "VALUE": 5.0, "AEXISTS": 5.0, "JLINKED": 0.0}, "ODB.2013.D6": {"DBULK": 0.0, "ISOPEN": 0.0, "EFREE": 0.0, "GUPDATED": 0.0, "IDISCOVERABLE": 0.0, "BAVAILABLE": 0.0, "FLICENSE": 0.0, "HSUSTAINABLE": 0.0, "CMACHINEREADABLE": 0.0, "VALUE": 5.0, "AEXISTS": 5.0, "JLINKED": 0.0}, "ODB.2013.D8": {"DBULK": 0.0, "ISOPEN": 0.0, "EFREE": 0.0, "GUPDATED": 0.0, "IDISCOVERABLE": 0.0, "BAVAILABLE": 10.0, "FLICENSE": 0.0, "HSUSTAINABLE": 0.0, "CMACHINEREADABLE": 0.0, "VALUE": 15.0, "AEXISTS": 5.0, "JLINKED": 0.0}, "ODB.2013.D12": {"DBULK": 0.0, "ISOPEN": 0.0, "EFREE": 0.0, "GUPDATED": 0.0, "IDISCOVERABLE": 0.0, "BAVAILABLE": 0.0, "FLICENSE": 0.0, "HSUSTAINABLE": 0.0, "CMACHINEREADABLE": 0.0, "VALUE": 5.0, "AEXISTS": 5.0, "JLINKED": 0.0}, "ODB.2013.D16": {"DBULK": 0.0, "ISOPEN": 0.0, "EFREE": 0.0, "GUPDATED": 0.0, "IDISCOVERABLE": 0.0, "BAVAILABLE": 10.0, "FLICENSE": 0.0, "HSUSTAINABLE": 0.0, "CMACHINEREADABLE": 0.0, "VALUE": 15.0, "AEXISTS": 5.0, "JLINKED": 0.0}}}, "2013": {"observations": {"INNOVATION": {"value": 31.25, "rank": 33, "rank_change": null}, "IMPLEMENTATION": {"value": 36.0, "rank": 29, "rank_change": null}, "ODB.2013.C.INIT": {"value": 6.0, "rank": 21, "rank_change": null}, "ODB.2013.I.INC": {"value": 2.0, "rank": 4, "rank_change": null}, "ODB.2013.C.RTI": {"value": 3.0, "rank": 52, "rank_change": null}, "FH": {"value": 80.0, "rank": 36, "rank_change": null}, "UN.OSI": {"value": 0.5294, "rank": 41, "rank_change": null}, "ODB.2013.C.CITY": {"value": 4.0, "rank": 18, "rank_change": null}, "REGULATORY_AND_CIVIL": {"value": 59.0, "rank": 35, "rank_change": null}, "POLITICAL": {"value": 15.0, "rank": 42, "rank_change": null}, "ODB.2013.D7": {"value": 5.0, "rank": 47, "rank_change": null}, "ODB.2013.D8": {"value": 15.0, "rank": 13, "rank_change": null}, "GOVERNMENT_ACTION": {"value": 44.0, "rank": 45, "rank_change": null}, "ODB.2013.D6": {"value": 15.0, "rank": 28, "rank_change": null}, "ODB.2013.C.CSOC": {"value": 4.0, "rank": 42, "rank_change": null}, "ODB.2013.I.ENTR": {"value": 0.0, "rank": 38, "rank_change": null}, "READINESS": {"value": 46.0, "rank": 37, "rank_change": null}, "SOCIAL_POLICY": {"value": 50.0, "rank": 20, "rank_change": null}, "SOCIAL": {"value": 31.0, "rank": 9, "rank_change": null}, "ODB.2013.I.ECON": {"value": 0.0, "rank": 28, "rank_change": null}, "BUSINESS_AND_ENTREPRENEURSHIP": {"value": 40.0, "rank": 37, "rank_change": null}, "ACCOUNTABILITY": {"value": 29.0, "rank": 34, "rank_change": null}, "ODB.2013.D9": {"value": 5.0, "rank": 43, "rank_change": null}, "ODB.2013.D12": {"value": 65.0, "rank": 19, "rank_change": null}, "ODB.2013.C.SUPIN": {"value": 4.0, "rank": 13, "rank_change": null}, "IMPACT": {"value": 17.0, "rank": 32, "rank_change": null}, "ECONOMIC": {"value": 0.0, "rank": 43, "rank_change": null}, "ODB.2013.I.GOV": {"value": 0.0, "rank": 37, "rank_change": null}, "ODB.2013.D4": {"value": 75.0, "rank": 12, "rank_change": null}, "ODB.2013.D11": {"value": 45.0, "rank": 29, "rank_change": null}, "WB.NETUSERS": {"value": 55.8, "rank": 33, "rank_change": null}, "ODB.2013.D13": {"value": 5.0, "rank": 56, "rank_change": null}, "ODB.2013.D10": {"value": 70.0, "rank": 21, "rank_change": null}, "WEF.GCI.9.02": {"value": 4.106196425, "rank": 67, "rank_change": null}, "ODB.2013.I.ACCOUNT": {"value": 2.0, "rank": 25, "rank_change": null}, "ODB.2013.D14": {"value": 60.0, "rank": 18, "rank_change": null}, "ODB.2013.D1": {"value": 45.0, "rank": 26, "rank_change": null}, "ODB.2013.D15": {"value": 95.0, "rank": 1, "rank_change": null}, "WEF.GITR.8.01": {"value": 2.643030324, "rank": 75, "rank_change": null}, "ODB.2013.I.ENV": {"value": 1.0, "rank": 16, "rank_change": null}, "ODB": {"value": 35.0, "rank": 31, "rank_change": null}, "ODB.2013.C.TRAIN": {"value": 4.0, "rank": 27, "rank_change": null}, "ODB.2013.C.DPL": {"value": 9.0, "rank": 4, "rank_change": null}, "ODB.2013.D2": {"value": 5.0, "rank": 29, "rank_change": null}, "ODB.2013.D5": {"value": 15.0, "rank": 34, "rank_change": null}}, "stats": {"INNOVATION": {"median": 31.25, "mean": 31.25}, "IMPLEMENTATION": {"median": 36.0, "mean": 36.0}, "ODB.2013.C.INIT": {"median": 6.0, "mean": 6.0}, "ODB.2013.I.INC": {"median": 2.0, "mean": 2.0}, "ODB.2013.C.RTI": {"median": 3.0, "mean": 3.0}, "FH": {"median": 80.0, "mean": 80.0}, "UN.OSI": {"median": 0.5294, "mean": 0.5294}, "ODB.2013.C.CITY": {"median": 4.0, "mean": 4.0}, "REGULATORY_AND_CIVIL": {"median": 59.0, "mean": 59.0}, "POLITICAL": {"median": 15.0, "mean": 15.0}, "ODB.2013.D7": {"median": 5.0, "mean": 5.0}, "ODB.2013.D8": {"median": 15.0, "mean": 15.0}, "GOVERNMENT_ACTION": {"median": 44.0, "mean": 44.0}, "ODB.2013.D6": {"median": 15.0, "mean": 15.0}, "ODB.2013.C.CSOC": {"median": 4.0, "mean": 4.0}, "ODB.2013.I.ENTR": {"median": 0.0, "mean": 0.0}, "READINESS": {"median": 46.0, "mean": 46.0}, "SOCIAL_POLICY": {"median": 50.0, "mean": 50.0}, "SOCIAL": {"median": 31.0, "mean": 31.0}, "ODB.2013.I.ECON": {"median": 0.0, "mean": 0.0}, "BUSINESS_AND_ENTREPRENEURSHIP": {"median": 40.0, "mean": 40.0}, "ACCOUNTABILITY": {"median": 29.0, "mean": 29.0}, "ODB.2013.D9": {"median": 5.0, "mean": 5.0}, "ODB.2013.D12": {"median": 65.0, "mean": 65.0}, "ODB.2013.C.SUPIN": {"median": 4.0, "mean": 4.0}, "IMPACT": {"median": 17.0, "mean": 17.0}, "ECONOMIC": {"median": 0.0, "mean": 0.0}, "ODB.2013.I.GOV": {"median": 0.0, "mean": 0.0}, "ODB.2013.D4": {"median": 75.0, "mean": 75.0}, "ODB.2013.D11": {"median": 45.0, "mean": 45.0}, "WB.NETUSERS": {"median": 55.8, "mean": 55.8}, "ODB.2013.D13": {"median": 5.0, "mean": 5.0}, "ODB.2013.D10": {"median": 70.0, "mean": 70.0}, "WEF.GCI.9.02": {"median": 4.106196425, "mean": 4.106196425}, "ODB.2013.I.ACCOUNT": {"median": 2.0, "mean": 2.0}, "ODB.2013.D14": {"median": 60.0, "mean": 60.0}, "ODB.2013.D1": {"median": 45.0, "mean": 45.0}, "ODB.2013.D15": {"median": 95.0, "mean": 95.0}, "WEF.GITR.8.01": {"median": 2.643030324, "mean": 2.643030324}, "ODB.2013.I.ENV": {"median": 1.0, "mean": 1.0}, "ODB": {"median": 35.0, "mean": 35.0}, "ODB.2013.C.TRAIN": {"median": 4.0, "mean": 4.0}, "ODB.2013.C.DPL": {"median": 9.0, "mean": 9.0}, "ODB.2013.D2": {"median": 5.0, "mean": 5.0}, "ODB.2013.D5": {"median": 15.0, "mean": 15.0}}, "datasets": {"ODB.2013.D11": {"DBULK": 0.0, "ISOPEN": 0.0, "EFREE": 15.0, "GUPDATED": 0.0, "IDISCOVERABLE": 0.0, "BAVAILABLE": 10.0, "FLICENSE": 0.0, "HSUSTAINABLE": 0.0, "CMACHINEREADABLE": 15.0, "VALUE": 45.0, "AEXISTS": 5.0, "JLINKED": 0.0}, "ODB.2013.D1": {"DBULK": 0.0, "ISOPEN": 0.0, "EFREE": 15.0, "GUPDATED": 0.0, "IDISCOVERABLE": 0.0, "BAVAILABLE": 10.0, "FLICENSE": 0.0, "HSUSTAINABLE": 0.0, "CMACHINEREADABLE": 15.0, "VALUE": 45.0, "AEXISTS": 5.0, "JLINKED": 0.0}, "ODB.2013.D15": {"DBULK": 15.0, "ISOPEN": 1.0, "EFREE": 15.0, "GUPDATED": 10.0, "IDISCOVERABLE": 5.0, "BAVAILABLE": 10.0, "FLICENSE": 15.0, "HSUSTAINABLE": 5.0, "CMACHINEREADABLE": 15.0, "VALUE": 95.0, "AEXISTS": 5.0, "JLINKED": 0.0}, "ODB.2013.D14": {"DBULK": 0.0, "ISOPEN": 0.0, "EFREE": 15.0, "GUPDATED": 10.0, "IDISCOVERABLE": 5.0, "BAVAILABLE": 10.0, "FLICENSE": 0.0, "HSUSTAINABLE": 0.0, "CMACHINEREADABLE": 15.0, "VALUE": 60.0, "AEXISTS": 5.0, "JLINKED": 0.0}, "ODB.2013.D4": {"DBULK": 0.0, "ISOPEN": 0.0, "EFREE": 15.0, "GUPDATED": 10.0, "IDISCOVERABLE": 5.0, "BAVAILABLE": 10.0, "FLICENSE": 15.0, "HSUSTAINABLE": 0.0, "CMACHINEREADABLE": 15.0, "VALUE": 75.0, "AEXISTS": 5.0, "JLINKED": 0.0}, "ODB.2013.D5": {"DBULK": 0.0, "ISOPEN": 0.0, "EFREE": 0.0, "GUPDATED": 0.0, "IDISCOVERABLE": 0.0, "BAVAILABLE": 10.0, "FLICENSE": 0.0, "HSUSTAINABLE": 0.0, "CMACHINEREADABLE": 0.0, "VALUE": 15.0, "AEXISTS": 5.0, "JLINKED": 0.0}, "ODB.2013.D13": {"DBULK": 0.0, "ISOPEN": 0.0, "EFREE": 0.0, "GUPDATED": 0.0, "IDISCOVERABLE": 0.0, "BAVAILABLE": 0.0, "FLICENSE": 0.0, "HSUSTAINABLE": 0.0, "CMACHINEREADABLE": 0.0, "VALUE": 5.0, "AEXISTS": 5.0, "JLINKED": 0.0}, "ODB.2013.D10": {"DBULK": 15.0, "ISOPEN": 0.0, "EFREE": 15.0, "GUPDATED": 10.0, "IDISCOVERABLE": 0.0, "BAVAILABLE": 10.0, "FLICENSE": 0.0, "HSUSTAINABLE": 0.0, "CMACHINEREADABLE": 15.0, "VALUE": 70.0, "AEXISTS": 5.0, "JLINKED": 0.0}, "ODB.2013.D9": {"DBULK": 0.0, "ISOPEN": 0.0, "EFREE": 0.0, "GUPDATED": 0.0, "IDISCOVERABLE": 0.0, "BAVAILABLE": 0.0, "FLICENSE": 0.0, "HSUSTAINABLE": 0.0, "CMACHINEREADABLE": 0.0, "VALUE": 5.0, "AEXISTS": 5.0, "JLINKED": 0.0}, "ODB.2013.D2": {"DBULK": 0.0, "ISOPEN": 0.0, "EFREE": 0.0, "GUPDATED": 0.0, "IDISCOVERABLE": 0.0, "BAVAILABLE": 0.0, "FLICENSE": 0.0, "HSUSTAINABLE": 0.0, "CMACHINEREADABLE": 0.0, "VALUE": 5.0, "AEXISTS": 5.0, "JLINKED": 0.0}, "ODB.2013.D7": {"DBULK": 0.0, "ISOPEN": 0.0, "EFREE": 0.0, "GUPDATED": 0.0, "IDISCOVERABLE": 0.0, "BAVAILABLE": 0.0, "FLICENSE": 0.0, "HSUSTAINABLE": 0.0, "CMACHINEREADABLE": 0.0, "VALUE": 5.0, "AEXISTS": 5.0, "JLINKED": 0.0}, "ODB.2013.D8": {"DBULK": 0.0, "ISOPEN": 0.0, "EFREE": 0.0, "GUPDATED": 0.0, "IDISCOVERABLE": 0.0, "BAVAILABLE": 10.0, "FLICENSE": 0.0, "HSUSTAINABLE": 0.0, "CMACHINEREADABLE": 0.0, "VALUE": 15.0, "AEXISTS": 5.0, "JLINKED": 0.0}, "ODB.2013.D12": {"DBULK": 0.0, "ISOPEN": 0.0, "EFREE": 15.0, "GUPDATED": 0.0, "IDISCOVERABLE": 5.0, "BAVAILABLE": 10.0, "FLICENSE": 15.0, "HSUSTAINABLE": 0.0, "CMACHINEREADABLE": 15.0, "VALUE": 65.0, "AEXISTS": 5.0, "JLINKED": 0.0}, "ODB.2013.D6": {"DBULK": 0.0, "ISOPEN": 0.0, "EFREE": 0.0, "GUPDATED": 0.0, "IDISCOVERABLE": 0.0, "BAVAILABLE": 10.0, "FLICENSE": 0.0, "HSUSTAINABLE": 0.0, "CMACHINEREADABLE": 0.0, "VALUE": 15.0, "AEXISTS": 5.0, "JLINKED": 0.0}}}}, "area": "ARG"}